paraffin/.gitignore
paraffin/__init__.py
paraffin/cli.py
paraffin/lock.py
paraffin/stage.py
paraffin/utils.py
paraffin/db/__init__.py
paraffin/db/app.py
paraffin/db/models.py
paraffin/static/index.html
paraffin/static/vite.svg
paraffin/static/assets/index-0YTZm72H.js
paraffin/static/assets/index-Cu6rN0KC.css
paraffin/ui/__init__.py
paraffin/ui/app.py
paraffin-0.3.7.dist-info/METADATA
paraffin-0.3.7.dist-info/WHEEL
paraffin-0.3.7.dist-info/entry_points.txt
paraffin-0.3.7.dist-info/licenses/LICENSE
paraffin-0.3.7.dist-info/RECORD
