Metadata-Version: 2.4
Name: paraffin
Version: 0.3.7
Summary: Parallel execution of DVC stages
Project-URL: Repository, https://github.com/zincware/paraffin
Project-URL: Releases, https://github.com/zincware/paraffin/releases
Author-email: Fabian Zills <fzills@icp.uni-stuttgart.de>
License-Expression: Apache-2.0
License-File: LICENSE
Requires-Python: >=3.10
Requires-Dist: dvc>=3.59.0
Requires-Dist: fastapi[standard]>=0.115.7
Requires-Dist: sqlmodel>=0.0.22
Requires-Dist: typer>=0.13
